setup.py
lanzajoke/__init__.py
lanzajoke/text.py
lanzajoke.egg-info/PKG-INFO
lanzajoke.egg-info/SOURCES.txt
lanzajoke.egg-info/dependency_links.txt
lanzajoke.egg-info/not-zip-safe
lanzajoke.egg-info/top_level.txt