Metadata-Version: 1.0
Name: lanzajoke
Version: 0.2
Summary: The funniest joke in the world
Home-page: http://github.com/lanza/lanzajoke
Author: Nathan Lanza
Author-email: nathan@lanza.io
License: MIT
Platform: UNKNOWN
